peakrdl_cocotb_ralgen-0.1.7.post9.dist-info/METADATA
peakrdl_cocotb_ralgen-0.1.7.post9.dist-info/WHEEL
peakrdl_cocotb_ralgen-0.1.7.post9.dist-info/entry_points.txt
peakrdl_cocotb_ralgen-0.1.7.post9.dist-info/licenses/LICENSE
peakrdl_cocotb_ralgen/__init__.py
peakrdl_cocotb_ralgen/__peakrdl__.py
peakrdl_cocotb_ralgen/callbacks/__init__.py
peakrdl_cocotb_ralgen/callbacks/bsv.py
peakrdl_cocotb_ralgen/callbacks/callback_base.py
peakrdl_cocotb_ralgen/cli.py
peakrdl_cocotb_ralgen/exporter.py
peakrdl_cocotb_ralgen/ralgen.py
peakrdl_cocotb_ralgen/templates/ralgen.j2
peakrdl_cocotb_ralgen/testcases/__init__.py
peakrdl_cocotb_ralgen/testcases/reset_test.py
peakrdl_cocotb_ralgen/testcases/rw_test.py
peakrdl_cocotb_ralgen-0.1.7.post9.dist-info/RECORD
