Metadata-Version: 2.1
Name: peakrdl-cocotb-ralgen
Version: 0.1.7.post9
Summary: Generate RAL tests from systemRDL.
Author-Email: Vijayvithal Jahagirdar <jahagirdar.vs@gmail.com>
License: MIT
Project-URL: Homepage, https://dyumnin.com/cocotb_ralgen
Project-URL: Repository, https://github.com/dyumnin/cocotb-ralgen.git
Project-URL: Issues, https://github.com/dyumnin/cocotb-ralgen/issues
Project-URL: Documentation, https://dyumnin.github.io/cocotb-ralgen
Requires-Python: >=3.10
Requires-Dist: systemrdl-compiler>=1.27.3
Requires-Dist: jinja2>=3.1.4
Requires-Dist: peakrdl>=1.1.0
